sharevia/__init__.py
sharevia/__main__.py
sharevia/main.py
sharevia/shareni.py
sharevia/test.py
sharevia/test2.py
sharevia-0.1.1.dist-info/METADATA
sharevia-0.1.1.dist-info/WHEEL
sharevia-0.1.1.dist-info/top_level.txt
sharevia-0.1.1.dist-info/RECORD
