Metadata-Version: 2.1
Name: sharevia
Version: 0.1.1
Summary: Sharevia - Single Line Multi Device Sharing Tool
Author: Neetish Singh(AAYS Analytics)
Author-email: <neetishsingh97@gmail.com>
Keywords: python,server,fastapi,shareit,xender,png,multi,smart,wifi,secure
Classifier: Development Status :: 1 - Planning
Classifier: Intended Audience :: Developers
Classifier: Programming Language :: Python :: 3
Classifier: Operating System :: Unix
Classifier: Operating System :: MacOS :: MacOS X
Classifier: Operating System :: Microsoft :: Windows
Requires-Dist: typing
Requires-Dist: uvicorn
Requires-Dist: fastapi
Requires-Dist: pyqrcode
Requires-Dist: pypng
